embargo_roller/__init__.py
embargo_roller/cli.py
embargo_roller/logger.py
embargo_roller/processor.py
embargo_roller/utils.py
eida_embargo_roller-1.0.2.dist-info/LICENSE
eida_embargo_roller-1.0.2.dist-info/METADATA
eida_embargo_roller-1.0.2.dist-info/WHEEL
eida_embargo_roller-1.0.2.dist-info/entry_points.txt
eida_embargo_roller-1.0.2.dist-info/top_level.txt
eida_embargo_roller-1.0.2.dist-info/RECORD
