Metadata-Version: 2.2
Name: eida-embargo-roller
Version: 1.0.2
Author-email: Nikos Sokos <nsokos@noa.gr>, Jonathan Schaeffer <jonathan.schaeffer@cnrs.fr>, Kostas Boukouras <kbouk@noa.gr>
Requires-Python: <4.0,>=3.11
License-File: LICENSE
Requires-Dist: click-log<1.0.0,>=0.4.0
Requires-Dist: pendulum>=3.0.0
Requires-Dist: obspy<2.0.0,>=1.4.0
Requires-Dist: setuptools>=75.6.0
Requires-Dist: pytest>=8.3.4
